{
    "R1": {
        "train_loss": 0.0070846108719706535,
        "train_acc": 96.1899995803833,
        "test_loss": 0.007047923281788826,
        "test_acc": 92.5,
        "convergence": 17.124786376953125,
        "R1": 1,
        "dataset_config": {
            "name": "CIFAR100",
            "noise_std": 0,
            "channels": 3,
            "width": 32,
            "height": 32,
            "validation_split": 0.2,
            "training_sample": 50000,
            "testing_sample": 10000,
            "out_channels": 2,
            "num_workers": 0,
            "seed": 0,
            "shuffle": true,
            "batch_size": 64,
            "augmentation": false,
            "zca_whitened": false,
            "training_class": "all",
            "split": "train",
            "nb_epoch": 50,
            "print_freq": 10,
            "validation": false,
            "continual_learning": true,
            "old_dataset_size": 32,
            "n_classes": 2,
            "selected_classes": [
                4,
                6
            ]
        },
        "dataset_sup": {
            "name": "CIFAR100",
            "noise_std": 0,
            "channels": 3,
            "width": 32,
            "height": 32,
            "validation_split": 0.2,
            "training_sample": 50000,
            "testing_sample": 10000,
            "out_channels": 2,
            "num_workers": 0,
            "seed": 0,
            "shuffle": true,
            "batch_size": 64,
            "augmentation": false,
            "zca_whitened": false,
            "training_class": "all",
            "split": "train",
            "nb_epoch": 50,
            "print_freq": 10,
            "validation": false,
            "continual_learning": true,
            "old_dataset_size": 32,
            "n_classes": 2,
            "selected_classes": [
                4,
                6
            ]
        },
        "dataset_unsup": {
            "name": "CIFAR100",
            "noise_std": 0,
            "channels": 3,
            "width": 32,
            "height": 32,
            "validation_split": 0.2,
            "training_sample": 50000,
            "testing_sample": 10000,
            "out_channels": 2,
            "num_workers": 0,
            "seed": 0,
            "shuffle": true,
            "batch_size": 10,
            "augmentation": false,
            "zca_whitened": false,
            "training_class": "all",
            "split": "train",
            "nb_epoch": 1,
            "print_freq": 50,
            "validation": false,
            "continual_learning": true,
            "old_dataset_size": 32,
            "n_classes": 2,
            "selected_classes": [
                4,
                6
            ]
        },
        "train_config": {
            "t1": {
                "blocks": [
                    0,
                    1,
                    2,
                    3
                ],
                "lr": 0.001,
                "mode": "hybrid",
                "batch_size": 64,
                "nb_epoch": 50,
                "print_freq": 10
            }
        }
    },
    "R2": {
        "train_loss": 0.003837605705484748,
        "train_acc": 97.58999943733215,
        "test_loss": 0.004264910705387592,
        "test_acc": 93.5,
        "convergence": 12.418567657470703,
        "R1": 1,
        "dataset_config": {
            "name": "CIFAR100",
            "noise_std": 0,
            "channels": 3,
            "width": 32,
            "height": 32,
            "validation_split": 0.2,
            "training_sample": 50000,
            "testing_sample": 10000,
            "out_channels": 2,
            "num_workers": 0,
            "seed": 0,
            "shuffle": true,
            "batch_size": 64,
            "augmentation": false,
            "zca_whitened": false,
            "training_class": "all",
            "split": "train",
            "nb_epoch": 50,
            "print_freq": 10,
            "validation": false,
            "continual_learning": true,
            "old_dataset_size": 32,
            "n_classes": 2,
            "selected_classes": [
                3,
                7
            ]
        },
        "dataset_sup": {
            "name": "CIFAR100",
            "noise_std": 0,
            "channels": 3,
            "width": 32,
            "height": 32,
            "validation_split": 0.2,
            "training_sample": 50000,
            "testing_sample": 10000,
            "out_channels": 2,
            "num_workers": 0,
            "seed": 0,
            "shuffle": true,
            "batch_size": 64,
            "augmentation": false,
            "zca_whitened": false,
            "training_class": "all",
            "split": "train",
            "nb_epoch": 50,
            "print_freq": 10,
            "validation": false,
            "continual_learning": true,
            "old_dataset_size": 32,
            "n_classes": 2,
            "selected_classes": [
                3,
                7
            ]
        },
        "dataset_unsup": {
            "name": "CIFAR100",
            "noise_std": 0,
            "channels": 3,
            "width": 32,
            "height": 32,
            "validation_split": 0.2,
            "training_sample": 50000,
            "testing_sample": 10000,
            "out_channels": 2,
            "num_workers": 0,
            "seed": 0,
            "shuffle": true,
            "batch_size": 10,
            "augmentation": false,
            "zca_whitened": false,
            "training_class": "all",
            "split": "train",
            "nb_epoch": 1,
            "print_freq": 50,
            "validation": false,
            "continual_learning": true,
            "old_dataset_size": 32,
            "n_classes": 2,
            "selected_classes": [
                3,
                7
            ]
        },
        "train_config": {
            "t1": {
                "blocks": [
                    0,
                    1,
                    2,
                    3
                ],
                "lr": 0.001,
                "mode": "hybrid",
                "batch_size": 64,
                "nb_epoch": 50,
                "print_freq": 10
            }
        }
    },
    "eval_1": {
        "test_loss": 0.012282857671380043,
        "test_acc": 84.0,
        "convergence": 23.989980697631836,
        "R1": 0,
        "dataset_sup": {
            "name": "CIFAR100",
            "noise_std": 0,
            "channels": 3,
            "width": 32,
            "height": 32,
            "validation_split": 0.2,
            "training_sample": 50000,
            "testing_sample": 10000,
            "out_channels": 2,
            "num_workers": 0,
            "seed": 0,
            "shuffle": true,
            "batch_size": 64,
            "augmentation": false,
            "zca_whitened": false,
            "training_class": "all",
            "split": "train",
            "nb_epoch": 50,
            "print_freq": 10,
            "validation": false,
            "continual_learning": true,
            "old_dataset_size": 32,
            "n_classes": 2,
            "selected_classes": [
                4,
                6
            ]
        },
        "dataset_unsup": {
            "name": "CIFAR100",
            "noise_std": 0,
            "channels": 3,
            "width": 32,
            "height": 32,
            "validation_split": 0.2,
            "training_sample": 50000,
            "testing_sample": 10000,
            "out_channels": 2,
            "num_workers": 0,
            "seed": 0,
            "shuffle": true,
            "batch_size": 10,
            "augmentation": false,
            "zca_whitened": false,
            "training_class": "all",
            "split": "train",
            "nb_epoch": 1,
            "print_freq": 50,
            "validation": false,
            "continual_learning": true,
            "old_dataset_size": 32,
            "n_classes": 2,
            "selected_classes": [
                4,
                6
            ]
        }
    },
    "cl_hyper": {
        "training_mode": "simultaneous",
        "cf_sol": false,
        "head_sol": true,
        "top_k": 0.5,
        "high_lr": 0.0,
        "low_lr": 1.0,
        "t_criteria": "mean",
        "delta_w_interval": 100.0,
        "heads_basis_t": 0.7675000000000001,
        "selected_classes": [
            [
                4,
                6
            ],
            [
                3,
                7
            ]
        ]
    }
}